ggmt/__init__.py
ggmt/cli.py
ggmt/matchticker.py
ggmt/tournament.py
ggmt-0.9.3.dist-info/DESCRIPTION.rst
ggmt-0.9.3.dist-info/METADATA
ggmt-0.9.3.dist-info/RECORD
ggmt-0.9.3.dist-info/WHEEL
ggmt-0.9.3.dist-info/entry_points.txt
ggmt-0.9.3.dist-info/metadata.json
ggmt-0.9.3.dist-info/top_level.txt
