Metadata-Version: 2.0
Name: ggmt
Version: 0.9.3
Summary: Good Game Match Ticker - command line application for tracking matches of various e-sport games
Home-page: https://github.com/Granitosaurus/ggmt
Author: Bernardas Ališauskas
Author-email: bernardas.alisauskas@gmail.com
License: GPLV3+
Platform: UNKNOWN
Classifier: Development Status :: 4 - Beta
Classifier: Environment :: Console
Classifier: Intended Audience :: End Users/Desktop
Classifier: Topic :: Games/Entertainment
Classifier: Operating System :: POSIX
Classifier: Programming Language :: Python
Classifier: License :: OSI Approved :: GNU General Public License v3 or later (GPLv3+)
Requires-Dist: click
Requires-Dist: requests
Requires-Dist: parsel
Requires-Dist: jinja2
